mathpylib/__init__.py
mathpylib/__main__.py
mathpylib/interp.py
mathpylib-0.1.dist-info/METADATA
mathpylib-0.1.dist-info/WHEEL
mathpylib-0.1.dist-info/entry_points.txt
mathpylib-0.1.dist-info/top_level.txt
mathpylib-0.1.dist-info/RECORD
